bbbc_datasets/__init__.py
bbbc_datasets/dataset_manager.py
bbbc_datasets/datasets/__init__.py
bbbc_datasets/datasets/base_dataset.py
bbbc_datasets/datasets/bbbc003.py
bbbc_datasets/datasets/bbbc004.py
bbbc_datasets/datasets/bbbc005.py
bbbc_datasets/datasets/bbbc006.py
bbbc_datasets/datasets/bbbc008.py
bbbc_datasets/datasets/bbbc010.py
bbbc_datasets/datasets/bbbc024.py
bbbc_datasets/datasets/bbbc027.py
bbbc_datasets/datasets/bbbc028.py
bbbc_datasets/datasets/bbbc029.py
bbbc_datasets/datasets/bbbc032.py
bbbc_datasets/datasets/bbbc033.py
bbbc_datasets/datasets/bbbc034.py
bbbc_datasets/datasets/bbbc035.py
bbbc_datasets/datasets/bbbc038.py
bbbc_datasets/datasets/bbbc039.py
bbbc_datasets/datasets/bbbc046.py
bbbc_datasets/datasets/bbbc050.py
bbbc_datasets/datasets/cellpose.py
bbbc_datasets/datasets/evican.py
bbbc_datasets/datasets/isbi15.py
bbbc_datasets/datasets/livecell.py
bbbc_datasets/datasets/sartorius.py
bbbc_datasets/utils/__init__.py
bbbc_datasets/utils/downloader.py
bbbc_datasets/utils/file_io.py
tests/__init__.py
tests/test_dataset_loading.py
tests/test_urls.py
bbbc_datasets-0.1.6.dist-info/LICENSE
bbbc_datasets-0.1.6.dist-info/METADATA
bbbc_datasets-0.1.6.dist-info/WHEEL
bbbc_datasets-0.1.6.dist-info/top_level.txt
bbbc_datasets-0.1.6.dist-info/RECORD
