Metadata-Version: 2.2
Name: bbbc_datasets
Version: 0.1.6
Summary: PyTorch-compatible dataset manager for BBBC datasets
Home-page: https://github.com/mario-koddenbrock/bbbc_datasets
Author: Mario Koddenbrock
Author-email: koddenbrock@gmail.com
Classifier: Programming Language :: Python :: 3
Classifier: License :: OSI Approved :: MIT License
Classifier: Operating System :: OS Independent
Requires-Python: >=3.6
License-File: LICENSE
Requires-Dist: torch
Requires-Dist: torchvision
Requires-Dist: numpy
Requires-Dist: tifffile
Requires-Dist: opencv-python
Requires-Dist: requests
Requires-Dist: matplotlib
Dynamic: author
Dynamic: author-email
Dynamic: classifier
Dynamic: description
Dynamic: description-content-type
Dynamic: home-page
Dynamic: requires-dist
Dynamic: requires-python
Dynamic: summary
